<?xml version='1.0' encoding='utf8'?>
<SHOPITEM>
   <ITEM_ID>534658</ITEM_ID>
   <PRODUCTNAME>Psaním ke svobodě - Mark Matousek</PRODUCTNAME>
   <EAN>9788075004314</EAN>
   <ISBN>978-80-7500-431-4</ISBN>
   <PRICE_VAT>200</PRICE_VAT>
   <DESCRIPTION>

Změníte-li svůj příběh, promění se i váš život. Kniha Psaním ke svobodě nabízí inspiraci k prozkoumání sebe sama prostřednictvím expresivního psaní. Provede vás cestou k probuzení pomocí radikálního odhalování pravdy a sebereflexe.

</DESCRIPTION>
   <CATEGORYTEXT>E-knihy | Astrologie, ezoterika | Ostatní</CATEGORYTEXT>
   <URL>
https://www.sckn.cz/psanim-ke-svobod-mark-matousek-pn-534-658/
</URL>
   <IMGURL>
https://www.sckn.cz/file/image/optimized/product-main/large/a4bf5b3cf3934b19964f6ef50285d05d.jpg
</IMGURL>
   <PARAMS>
      <PARAM>
         <PARAM_NAME>Počet stran</PARAM_NAME>
         <VAL>243</VAL>
      </PARAM>
      <PARAM>
         <PARAM_NAME>Datum vydání</PARAM_NAME>
         <VAL>2018</VAL>
      </PARAM>
      <PARAM>
         <PARAM_NAME>Pořadí vydání</PARAM_NAME>
         <VAL>neurčeno</VAL>
      </PARAM>
   </PARAMS>
   <CONTRIBUTORS>
      <CONTRIBUTOR>
         <ROLE>Autor</ROLE>
         <NAME>Mark</NAME>
         <SURNAME>Matousek</SURNAME>
      </CONTRIBUTOR>
      <CONTRIBUTOR>
         <ROLE>Autor</ROLE>
         <NAME>Adam</NAME>
         <SURNAME>Pumpr</SURNAME>
      </CONTRIBUTOR>
   </CONTRIBUTORS>
</SHOPITEM>
