<?xml version='1.0' encoding='utf8'?>
<SHOPITEM>
   <ITEM_ID>534154</ITEM_ID>
   <PRODUCTNAME>Nenasytná - Jana Javorská</PRODUCTNAME>
   <EAN>9788075896650</EAN>
   <ISBN>978-80-7589-665-0</ISBN>
   <PRICE_VAT>129</PRICE_VAT>
   <DESCRIPTION>

SEX - je opět hlavním tématem další knihy autorky Jany Javorské. Jak se může stát z usazené manželky, která nezná nic jiného než nudu všedního života, zaměstnání, péči o rodinu a manžela, vášnivá a nenasytná milenka prahnoucí dnes a denně po sexu?

</DESCRIPTION>
   <CATEGORYTEXT />
   <URL>
https://www.sckn.cz/nenasytna-jana-javorska-pn-534-154/
</URL>
   <IMGURL>
https://www.sckn.cz/file/image/optimized/product-main/large/6a90c3fc5ef9a60760536910e6e4a8cf.jpg
</IMGURL>
   <PARAMS>
      <PARAM>
         <PARAM_NAME>Počet stran</PARAM_NAME>
         <VAL>182</VAL>
      </PARAM>
      <PARAM>
         <PARAM_NAME>Datum vydání</PARAM_NAME>
         <VAL>2018</VAL>
      </PARAM>
      <PARAM>
         <PARAM_NAME>Pořadí vydání</PARAM_NAME>
         <VAL>neurčeno</VAL>
      </PARAM>
   </PARAMS>
   <CONTRIBUTORS>
      <CONTRIBUTOR>
         <ROLE>Autor</ROLE>
         <NAME>Jana</NAME>
         <SURNAME>Javorská</SURNAME>
      </CONTRIBUTOR>
   </CONTRIBUTORS>
</SHOPITEM>
