<?xml version='1.0' encoding='utf8'?>
<SHOPITEM>
<ITEM_ID>534239</ITEM_ID>
<PRODUCTNAME>V zajetí zlaté řeky</PRODUCTNAME>
<PRODUCT>V zajetí zlaté řeky</PRODUCT>
<EAN>9788075438553</EAN>
<ISBN>978-80-7543-855-3</ISBN>
<PRICE_VAT>269</PRICE_VAT>
<DESCRIPTION>

Adam Stark narazil na zlato. Spolu se ženou a sestrou se snaží vytěžit co nejvíce, zatímco se jim ve spleti vyprahlých kaňonů daří unikat pozornosti Apačů. Znenadání se objeví psanec Taggart pronásledovaný lovcem odměn...

</DESCRIPTION>
<CATEGORYTEXT>
Tištěné knihy | Krásná literatura | Próza | Světová próza
</CATEGORYTEXT>
<URL>
https://www.sckn.cz/v-zajeti-zlate-eky-louis-l-acute-amour-pn-534-239/
</URL>
<IMGURL>
https://www.sckn.cz/file/image/optimized/product-main/large/637d8966ca2d19cd96c78ce752ed8858.jpg
</IMGURL>
<PARAM>
<PARAM_NAME>Počet stran</PARAM_NAME>
<VAL>192</VAL>
</PARAM>
<PARAM>
<PARAM_NAME>Datum vydání</PARAM_NAME>
<VAL>2018</VAL>
</PARAM>
<PARAM>
<PARAM_NAME>Vazba</PARAM_NAME>
<VAL>kniha, vázaná vazba</VAL>
</PARAM>
<PARAM>
<PARAM_NAME>Pořadí vydání</PARAM_NAME>
<VAL>neurčeno</VAL>
</PARAM>
<PARAM>
<PARAM_NAME>Jazyk</PARAM_NAME>
<VAL>český</VAL>
</PARAM>
<CONTRIBUTOR>
<ROLE>Autor</ROLE>
<NAME>Louis</NAME>
<SURNAME>L´Amour</SURNAME>
</CONTRIBUTOR>
<THEMATIC_GROUP>13 - Krásná literatura</THEMATIC_GROUP>
</SHOPITEM>
