<?xml version='1.0' encoding='utf8'?>
<SHOPITEM>
<ITEM_ID>534614</ITEM_ID>
<PRODUCTNAME>Tajný deník Blanky z Valois - Melita Denková</PRODUCTNAME>
<PRODUCT>Tajný deník Blanky z Valois - Melita Denková</PRODUCT>
<EAN>9788075438256</EAN>
<ISBN>978-80-7543-825-6</ISBN>
<PRICE_VAT>189</PRICE_VAT>
<DESCRIPTION>

Ze čtyř žen Karla IV. je Blanka z Valois považována za tu nejmilovanější. Příběh začíná v lednu 1336, kdy je vznešenému páru teprve devatenáct let. Do Prahy přijíždí druhá žena Karlova otce Jana Lucemburského...

</DESCRIPTION>
<URL>
https://www.sckn.cz/tajny-denik-blanky-z-valois-melita-denkova-pn-534-614/
</URL>
<IMGURL>
https://www.sckn.cz/file/image/optimized/product-main/large/4d52831306d07f6f4eb4e3b69794a85b.jpg
</IMGURL>
<PARAM>
<PARAM_NAME>Počet stran</PARAM_NAME>
<VAL>224</VAL>
</PARAM>
<PARAM>
<PARAM_NAME>Datum vydání</PARAM_NAME>
<VAL>2018</VAL>
</PARAM>
<PARAM>
<PARAM_NAME>Pořadí vydání</PARAM_NAME>
<VAL>neurčeno</VAL>
</PARAM>
<CONTRIBUTOR>
<ROLE>Autor</ROLE>
<NAME>Melita</NAME>
<SURNAME>Denková</SURNAME>
</CONTRIBUTOR>
<THEMATIC_GROUP>999 - nezařazeno</THEMATIC_GROUP>
</SHOPITEM>
