<?xml version='1.0' encoding='utf8'?>
<SHOPITEM>
<ITEM_ID>533800</ITEM_ID>
<PRODUCTNAME>
Lucifer junior 2 – Pekelně dobrá parta - Jochen Till
</PRODUCTNAME>
<PRODUCT>
Lucifer junior 2 – Pekelně dobrá parta - Jochen Till
</PRODUCT>
<EAN>9788075410849</EAN>
<ISBN>978-80-7541-084-9</ISBN>
<PRICE_VAT>249</PRICE_VAT>
<DESCRIPTION>

Lucifer junior se právě vrátil z prázdnin, které trávil doma v pekle, do školy u svatého Fidibuse. A tam už na něj čeká spousta starostí.

</DESCRIPTION>
<URL>
https://www.sckn.cz/lucifer-junior-2-ndash-pekeln-dobra-parta-jochen-till-pn-533-800/
</URL>
<IMGURL>
https://www.sckn.cz/file/image/optimized/product-main/large/e3f6bf9ce071a60a5c8247ff82e46500.jpg
</IMGURL>
<PARAM>
<PARAM_NAME>Počet stran</PARAM_NAME>
<VAL>220</VAL>
</PARAM>
<PARAM>
<PARAM_NAME>Datum vydání</PARAM_NAME>
<VAL>2018</VAL>
</PARAM>
<PARAM>
<PARAM_NAME>Vazba</PARAM_NAME>
<VAL>kniha, vázaná vazba</VAL>
</PARAM>
<PARAM>
<PARAM_NAME>Pořadí vydání</PARAM_NAME>
<VAL>neurčeno</VAL>
</PARAM>
<CONTRIBUTOR>
<ROLE>Autor</ROLE>
<NAME>Dagmar</NAME>
<SURNAME>Burešová</SURNAME>
</CONTRIBUTOR>
<CONTRIBUTOR>
<ROLE>Autor</ROLE>
<NAME>Jochen</NAME>
<SURNAME>Till</SURNAME>
</CONTRIBUTOR>
<THEMATIC_GROUP>999 - nezařazeno</THEMATIC_GROUP>
</SHOPITEM>
