<?xml version='1.0' encoding='utf8'?>
<SHOPITEM>
<ITEM_ID>534608</ITEM_ID>
<PRODUCTNAME>
Dětská encyklopedie - Kniha, která všechno vysvětlí
</PRODUCTNAME>
<PRODUCT>
Dětská encyklopedie - Kniha, která všechno vysvětlí
</PRODUCT>
<EAN>9788075850553</EAN>
<ISBN>978-80-7585-055-3</ISBN>
<PRICE_VAT>499</PRICE_VAT>
<DESCRIPTION>

Kniha „Dětská encyklopedie“ (nakladatelství Dorling Kindersley, Velká Británie) je bohatě ilustrovaná publikace pro mladé čtenáře. Její podtitul „Kniha, která všechno vysvětlí“) je poměrně výstižný, protože obsahuje více než 250 důležitých hesel.

</DESCRIPTION>
<URL>
https://www.sckn.cz/d-tska-encyklopedie-kniha-ktera-v-scaron-echno-vysv-tli-pn-534-608/
</URL>
<PARAM>
<PARAM_NAME>Počet stran</PARAM_NAME>
<VAL>304</VAL>
</PARAM>
<PARAM>
<PARAM_NAME>Datum vydání</PARAM_NAME>
<VAL>2018</VAL>
</PARAM>
<PARAM>
<PARAM_NAME>Vazba</PARAM_NAME>
<VAL>kniha, vázaná vazba</VAL>
</PARAM>
<PARAM>
<PARAM_NAME>Pořadí vydání</PARAM_NAME>
<VAL>neurčeno</VAL>
</PARAM>
<THEMATIC_GROUP>999 - nezařazeno</THEMATIC_GROUP>
</SHOPITEM>
