<?xml version='1.0' encoding='utf8'?>
<SHOPITEM>
<ITEM_ID>534376</ITEM_ID>
<PRODUCTNAME>Cesta k osvícení</PRODUCTNAME>
<PRODUCT>Cesta k osvícení</PRODUCT>
<EAN>9788075498335</EAN>
<ISBN>978-80-7549-833-5</ISBN>
<PRICE_VAT>299</PRICE_VAT>
<DESCRIPTION>

Nová knížka, s níž se k nám obrací Jeho Svatost dalajalama, je mimořádně prospěšná i praktická.

</DESCRIPTION>
<CATEGORYTEXT>
Tištěné knihy | Filozofie a náboženství | Duchovní teorie a směry
</CATEGORYTEXT>
<URL>
https://www.sckn.cz/cesta-k-osviceni-jeho-svatost-dalajlama-xiv-jeffrey-hopkins-pn-534-376/
</URL>
<IMGURL>
https://www.sckn.cz/file/image/optimized/product-main/large/17539c6e9310887c05c684b4958bba0c.jpg
</IMGURL>
<PARAM>
<PARAM_NAME>Počet stran</PARAM_NAME>
<VAL>368</VAL>
</PARAM>
<PARAM>
<PARAM_NAME>Datum vydání</PARAM_NAME>
<VAL>2018</VAL>
</PARAM>
<PARAM>
<PARAM_NAME>Vazba</PARAM_NAME>
<VAL>kniha, vázaná vazba</VAL>
</PARAM>
<PARAM>
<PARAM_NAME>Pořadí vydání</PARAM_NAME>
<VAL>neurčeno</VAL>
</PARAM>
<PARAM>
<PARAM_NAME>Jazyk</PARAM_NAME>
<VAL>český</VAL>
</PARAM>
<CONTRIBUTOR>
<ROLE>Autor</ROLE>
<NAME>Jeho svatost Dalajlama</NAME>
<SURNAME>XIV.</SURNAME>
</CONTRIBUTOR>
<CONTRIBUTOR>
<ROLE>Autor</ROLE>
<NAME>Jeffrey</NAME>
<SURNAME>Hopkins</SURNAME>
</CONTRIBUTOR>
<THEMATIC_GROUP>0 - Teologie, duchovní nauky</THEMATIC_GROUP>
</SHOPITEM>
